setup.py
statisticspy/Binomialdistribution.py
statisticspy/Gaussiandistribution.py
statisticspy/Generaldistribution.py
statisticspy/__init__.py
statisticspy.egg-info/PKG-INFO
statisticspy.egg-info/SOURCES.txt
statisticspy.egg-info/dependency_links.txt
statisticspy.egg-info/not-zip-safe
statisticspy.egg-info/top_level.txt