Metadata-Version: 2.1
Name: statisticspy
Version: 0.1
Summary: Gaussian and Binominal distributions
Author: Albert Guo
Author-email: sub.jl@icloud.com
License: UNKNOWN
Platform: UNKNOWN
